dev_init.py
dev_init/dev_init.py
dev_init/_version.py
dev_init/__init__.py
dev_init-0.3.0.dist-info/DESCRIPTION.rst
dev_init-0.3.0.dist-info/entry_points.txt
dev_init-0.3.0.dist-info/METADATA
dev_init-0.3.0.dist-info/metadata.json
dev_init-0.3.0.dist-info/RECORD
dev_init-0.3.0.dist-info/top_level.txt
dev_init-0.3.0.dist-info/WHEEL
