Metadata-Version: 2.0
Name: dev-init
Version: 0.3.0
Summary: Automated development environment initialization
Home-page: https://github.com/rmed/dev-init
Author: Rafael Medina García
Author-email: rafamedgar@gmail.com
License: GPLv3
Keywords: development environment automated initialization dev init
Platform: UNKNOWN
Classifier: Development Status :: 5 - Production/Stable
Classifier: Intended Audience :: Developers
Classifier: Topic :: Software Development
Classifier: Topic :: Utilities
Classifier: License :: OSI Approved :: GNU General Public License v3 or later (GPLv3+)
Classifier: Programming Language :: Python :: 2
Classifier: Programming Language :: Python :: 2.7
Classifier: Programming Language :: Python :: 3
Classifier: Programming Language :: Python :: 3.3
Classifier: Programming Language :: Python :: 3.4
